[
  {
    "full_name": "withastro/astro",
    "stargazers_count": 40013,
    "open_issues_count": 140,
    "forks_count": 2122
  },
  {
    "full_name": "t3-oss/create-t3-turbo",
    "stargazers_count": 3732,
    "open_issues_count": 35,
    "forks_count": 305
  },
  {
    "full_name": "prisma/prisma",
    "stargazers_count": 36267,
    "open_issues_count": 3046,
    "forks_count": 1524
  },
  {
    "full_name": "CodeEditApp/CodeEdit",
    "stargazers_count": 19749,
    "open_issues_count": 169,
    "forks_count": 1092
  },
  {
    "full_name": "solidjs/solid-start",
    "stargazers_count": 4267,
    "open_issues_count": 53,
    "forks_count": 340
  },
  {
    "full_name": "solidjs/solid",
    "stargazers_count": 30493,
    "open_issues_count": 73,
    "forks_count": 885
  },
  {
    "full_name": "open-sauced/open-sauced",
    "stargazers_count": 913,
    "open_issues_count": 0,
    "forks_count": 848
  }
]